{"media":[{
            "type": "video",
            "url": "https://www.youtube.com/watch?v=kBQ6dN7n2WY",
            "thumbUrl": "localService/thumb/kBQ6dN7n2WY.jpg",
            "fav": "false",
            "lowResVideoPath": "localService/video/kBQ6dN7n2WY.mp4",
            "fitURL": "", 
            "name": "20.01.2018 Alte Mälzerei - 20 Jahre Shotter.mp4",
            "fileSize": 12506357,
            "date": 1517099409,
            "duration" :  12,
            "lensMode": "unknownLensMode"
        },{
            "type": "video",
            "url": "https://www.youtube.com/watch?v=tSJJw44bC7Y",
            "thumbUrl": "localService/thumb/tSJJw44bC7Y.jpg",
            "fav": "false",
            "lowResVideoPath": "localService/video/tSJJw44bC7Y.mp4",
            "fitURL": "", 
            "name": "SENA BT10-01 BLUETOOTH MIC TEST SOUND SAMPLE.mp4",
            "fileSize": 4131956,
            "date": 1514980897,
            "duration" :  4,
            "lensMode": "unknownLensMode"
        },{
            "type": "video",
            "url": "https://www.youtube.com/watch?v=2rwLYjZ-ios",
            "thumbUrl": "localService/thumb/2rwLYjZ-ios.jpg",
            "fav": "false",
            "lowResVideoPath": "localService/video/2rwLYjZ-ios.mp4",
            "fitURL": "", 
            "name": "SKATEHALLE REGENSBURG 10 TRIX PAUL SPANL.mp4",
            "fileSize": 4140525,
            "date": 1515023509,
            "duration" :  4,
            "lensMode": "unknownLensMode"
        },{
            "type": "video",
            "url": "https://www.youtube.com/watch?v=cVvVu7TZ7Kw",
            "thumbUrl": "localService/thumb/cVvVu7TZ7Kw.jpg",
            "fav": "false",
            "lowResVideoPath": "localService/video/cVvVu7TZ7Kw.mp4",
            "fitURL": "", 
            "name": "2018 - SKATEHALLE REGENSBURG LOS GEHT'S.mp4",
            "fileSize": 4234838,
            "date": 1515023509,
            "duration" :  4,
            "lensMode": "unknownLensMode"
        },{
            "type": "video",
            "url": "https://www.youtube.com/watch?v=STVlpvyyEGQ",
            "thumbUrl": "localService/thumb/STVlpvyyEGQ.jpg",
            "fav": "false",
            "lowResVideoPath": "localService/video/STVlpvyyEGQ.mp4",
            "fitURL": "", 
            "name": "FIRST SUNSET OLLIE 2018.mp4",
            "fileSize": 1519595,
            "date": 1517449019,
            "duration" :  1,
            "lensMode": "unknownLensMode"
        },{
            "type": "video",
            "url": "https://www.youtube.com/watch?v=Cee_1fTQexM",
            "thumbUrl": "localService/thumb/Cee_1fTQexM.jpg",
            "fav": "false",
            "lowResVideoPath": "localService/video/Cee_1fTQexM.mp4",
            "fitURL": "", 
            "name": "20100417 KILIAN SCHÖNER.mp4",
            "fileSize": 1263320,
            "date": 1513876142,
            "duration" :  1,
            "lensMode": "unknownLensMode"
        },{
            "type": "video",
            "url": "https://www.youtube.com/watch?v=nrrVz5Evk5A",
            "thumbUrl": "localService/thumb/nrrVz5Evk5A.jpg",
            "fav": "false",
            "lowResVideoPath": "localService/video/nrrVz5Evk5A.mp4",
            "fitURL": "", 
            "name": "DOWNHILL EIBRUNN MARTIN JOCHEN.mp4",
            "fileSize": 10902144,
            "date": 1513747436,
            "duration" :  10,
            "lensMode": "unknownLensMode"
        },{
            "type": "video",
            "url": "https://www.youtube.com/watch?v=m6hrVzo35ds",
            "thumbUrl": "localService/thumb/m6hrVzo35ds.jpg",
            "fav": "false",
            "lowResVideoPath": "localService/video/m6hrVzo35ds.mp4",
            "fitURL": "", 
            "name": "20170813 UPHILL.mp4",
            "fileSize": 3688744,
            "date": 1513747436,
            "duration" :  4,
            "lensMode": "unknownLensMode"
        },{
            "type": "video",
            "url": "https://www.youtube.com/watch?v=WIXyZwpAAHQ",
            "thumbUrl": "localService/thumb/WIXyZwpAAHQ.jpg",
            "fav": "false",
            "lowResVideoPath": "localService/video/WIXyZwpAAHQ.mp4",
            "fitURL": "", 
            "name": "30 SECONDS #TEAMHUG.mp4",
            "fileSize": 2749169,
            "date": 1509669263,
            "duration" :  3,
            "lensMode": "unknownLensMode"
        },{
            "type": "video",
            "url": "https://www.youtube.com/watch?v=PIN8KrM7sIg",
            "thumbUrl": "localService/thumb/PIN8KrM7sIg.jpg",
            "fav": "false",
            "lowResVideoPath": "localService/video/PIN8KrM7sIg.mp4",
            "fitURL": "", 
            "name": "HALLOWEEN BOWL JAM.mp4",
            "fileSize": 7257359,
            "date": 1513747406,
            "duration" :  7,
            "lensMode": "unknownLensMode"
        },{
            "type": "photo",
            "url": "localService/thumb/FztO3b2LSdw.jpg",
            "thumbUrl": "localService/thumb/FztO3b2LSdw.jpg",
            "fav": "false",
            "lowResVideoPath": "localService/video/FztO3b2LSdw.mp4",
            "fitURL": "", 
            "name": "BEATNUTS SKATEBATTLE 2017.mp4",
            "fileSize": 14697,
            "date": 1508619163,
            "duration" :  0,
            "lensMode": "unknownLensMode"
        },{
            "type": "photo",
            "url": "localService/thumb/7jZMXg14EtI.jpg",
            "thumbUrl": "localService/thumb/7jZMXg14EtI.jpg",
            "fav": "false",
            "lowResVideoPath": "localService/video/7jZMXg14EtI.mp4",
            "fitURL": "", 
            "name": "BEATNUTS SKATEBATTLE 2017 Siegerehrung.mp4",
            "fileSize": 19960,
            "date": 1508908536,
            "duration" :  0,
            "lensMode": "unknownLensMode"
        },{
            "type": "video",
            "url": "https://www.youtube.com/watch?v=Nsfq6PHsDJ4.mp4",
            "thumbUrl": "localService/thumb/Nsfq6PHsDJ4.jpg",
            "fav": "false",
            "lowResVideoPath": "localService/video/Nsfq6PHsDJ4.mp4",
            "fitURL": "", 
            "name": "20170416 Morass Skoffin - Scars of fear.mp4",
            "fileSize": 20788125,
            "date": 1505452553,
            "duration" :  20,
            "lensMode": "unknownLensMode"
        },{
            "type": "video",
            "url": "https://www.youtube.com/watch?v=cuMfBlbSnJw.mp4",
            "thumbUrl": "localService/thumb/cuMfBlbSnJw.jpg",
            "fav": "false",
            "lowResVideoPath": "localService/video/cuMfBlbSnJw.mp4",
            "fitURL": "", 
            "name": "20170806 SKATEPARK DEUERLING.mp4",
            "fileSize": 11564601,
            "date": 1507785093,
            "duration" :  11,
            "lensMode": "unknownLensMode"
        },{
            "type": "video",
            "url": "https://www.youtube.com/watch?v=y-MQd8IZdBY.mp4",
            "thumbUrl": "localService/thumb/y-MQd8IZdBY.jpg",
            "fav": "false",
            "lowResVideoPath": "localService/video/y-MQd8IZdBY.mp4",
            "fitURL": "", 
            "name": "20170806 SINZING.mp4",
            "fileSize": 7291577,
            "date": 1504560432,
            "duration" :  7,
            "lensMode": "unknownLensMode"
        },{
            "type": "video",
            "url": "https://www.youtube.com/watch?v=gXzFOdu4J40.mp4",
            "thumbUrl": "localService/thumb/gXzFOdu4J40.jpg",
            "fav": "false",
            "lowResVideoPath": "localService/video/gXzFOdu4J40.mp4",
            "fitURL": "", 
            "name": "SKATEBOARD CONTEST PETTENDORF.mp4",
            "fileSize": 9600557,
            "date": 1503854688,
            "duration" :  9,
            "lensMode": "unknownLensMode"
        },{
            "type": "video",
            "url": "https://www.youtube.com/watch?v=9KAmCRCoJTU.mp4",
            "thumbUrl": "localService/thumb/9KAmCRCoJTU.jpg",
            "fav": "false",
            "lowResVideoPath": "localService/video/9KAmCRCoJTU.mp4",
            "fitURL": "", 
            "name": "20170729 SKATEBOARD CONTEST PETTENDORF A GRUPPE.mp4",
            "fileSize": 10031963,
            "date": 1503854688,
            "duration" :  10,
            "lensMode": "unknownLensMode"
        },{
            "type": "video",
            "url": "https://www.youtube.com/watch?v=oZq80qxvu0I.mp4",
            "thumbUrl": "localService/thumb/oZq80qxvu0I.jpg",
            "fav": "false",
            "lowResVideoPath": "localService/video/oZq80qxvu0I.mp4",
            "fitURL": "", 
            "name": "20170729 SKATEBOARD CONTEST PETTENDORF C B GRUPPE.mp4",
            "fileSize": 8531371,
            "date": 1503854688,
            "duration" :  8,
            "lensMode": "unknownLensMode"
        },{
            "type": "video",
            "url": "https://www.youtube.com/watch?v=4d6RJwLZbrY.mp4",
            "thumbUrl": "localService/thumb/4d6RJwLZbrY.jpg",
            "fav": "false",
            "lowResVideoPath": "localService/video/4d6RJwLZbrY.mp4",
            "fitURL": "", 
            "name": "20170729 SKATEBOARD CONTEST PETTENDORF HIGHEST OLLIE.mp4",
            "fileSize": 1489783,
            "date": 1503854689,
            "duration" :  1,
            "lensMode": "unknownLensMode"
        },{
            "type": "photo",
            "url": "localService/thumb/LSDGISZ-eBE.jpg",
            "thumbUrl": "localService/thumb/LSDGISZ-eBE.jpg",
            "fav": "false",
            "lowResVideoPath": "localService/video/LSDGISZ-eBE.mp4",
            "fitURL": "", 
            "name": "'SKATE AND VIBES' SKATEBOARD CONTEST 2017 MARKTREDWITZ.mp4",
            "fileSize": 16131,
            "date": 1501601239,
            "duration" :  0,
            "lensMode": "unknownLensMode"
        },{
            "type": "video",
            "url": "https://www.youtube.com/watch?v=OuJ0FBliCpQ.mp4",
            "thumbUrl": "localService/thumb/OuJ0FBliCpQ.jpg",
            "fav": "false",
            "lowResVideoPath": "localService/video/OuJ0FBliCpQ.mp4",
            "fitURL": "", 
            "name": "TRAILER - SKATEBOARD CONTEST PETTENDORF.mp4",
            "fileSize": 8348346,
            "date": 1500873518,
            "duration" :  8,
            "lensMode": "unknownLensMode"
        },{
            "type": "video",
            "url": "https://www.youtube.com/watch?v=iX7X3JIQlPM.mp4",
            "thumbUrl": "localService/thumb/iX7X3JIQlPM.jpg",
            "fav": "false",
            "lowResVideoPath": "localService/video/iX7X3JIQlPM.mp4",
            "fitURL": "", 
            "name": "STALIN PLAZA 2017.mp4",
            "fileSize": 11495448,
            "date": 1500111168,
            "duration" :  11,
            "lensMode": "unknownLensMode"
        },{
            "type": "video",
            "url": "https://www.youtube.com/watch?v=46HpYb6DPWk.mp4",
            "thumbUrl": "localService/thumb/46HpYb6DPWk.jpg",
            "fav": "false",
            "lowResVideoPath": "localService/video/46HpYb6DPWk.mp4",
            "fitURL": "", 
            "name": "GO FOR THE BOWL - MYSTIC SK8 CUP 2017.mp4",
            "fileSize": 24006309,
            "date": 1497859383,
            "duration" :  23,
            "lensMode": "unknownLensMode"
        },{
            "type": "video",
            "url": "https://www.youtube.com/watch?v=_wRHQQhPxYk.mp4",
            "thumbUrl": "localService/thumb/_wRHQQhPxYk.jpg",
            "fav": "false",
            "lowResVideoPath": "localService/video/_wRHQQhPxYk.mp4",
            "fitURL": "", 
            "name": "20170528 SINZING SKATEPARK SESH.mp4",
            "fileSize": 4926149,
            "date": 1514680844,
            "duration" :  5,
            "lensMode": "unknownLensMode"
        },{
            "type": "video",
            "url": "https://www.youtube.com/watch?v=cprB_mbaa9U.mp4",
            "thumbUrl": "localService/thumb/cprB_mbaa9U.jpg",
            "fav": "false",
            "lowResVideoPath": "localService/video/cprB_mbaa9U.mp4",
            "fitURL": "", 
            "name": "20170603 NEUNBURG VORM WALD SKATEPARK ERÖFFNUNG.mp4",
            "fileSize": 8224679,
            "date": 1497571052,
            "duration" :  8,
            "lensMode": "unknownLensMode"
        },{
            "type": "video",
            "url": "https://www.youtube.com/watch?v=h5N81H0AF0U.mp4",
            "thumbUrl": "localService/thumb/h5N81H0AF0U.jpg",
            "fav": "false",
            "lowResVideoPath": "localService/video/h5N81H0AF0U.mp4",
            "fitURL": "", 
            "name": "MYSTIC SKATE CUP LADIES 2016.mp4",
            "fileSize": 8587960,
            "date": 1495929643,
            "duration" :  8,
            "lensMode": "unknownLensMode"
        },{
            "type": "video",
            "url": "https://www.youtube.com/watch?v=qbr_OJvP2mU.mp4",
            "thumbUrl": "localService/thumb/qbr_OJvP2mU.jpg",
            "fav": "false",
            "lowResVideoPath": "localService/video/qbr_OJvP2mU.mp4",
            "fitURL": "", 
            "name": "20170420 COUNTRYSIDE DIRT.mp4",
            "fileSize": 12524100,
            "date": 1497946437,
            "duration" :  12,
            "lensMode": "unknownLensMode"
        },{
            "type": "video",
            "url": "https://www.youtube.com/watch?v=4u9jj_8e63I.mp4",
            "thumbUrl": "localService/thumb/4u9jj_8e63I.jpg",
            "fav": "false",
            "lowResVideoPath": "localService/video/4u9jj_8e63I.mp4",
            "fitURL": "", 
            "name": "SINZING SKATEPARK SESSION.mp4",
            "fileSize": 9960671,
            "date": 1492217431,
            "duration" :  9,
            "lensMode": "unknownLensMode"
        },{
            "type": "photo",
            "url": "localService/thumb/IKH_6-56Qwo.jpg",
            "thumbUrl": "localService/thumb/IKH_6-56Qwo.jpg",
            "fav": "false",
            "lowResVideoPath": "localService/video/IKH_6-56Qwo.mp4",
            "fitURL": "", 
            "name": "0010| SKATEHALLE RGENEBSURG STEPHAN SAWALLISCH.mp4",
            "fileSize": 21679,
            "date": 1492106146,
            "duration" :  0,
            "lensMode": "unknownLensMode"
        },{
            "type": "photo",
            "url": "localService/thumb/F46IQC7InJk.jpg",
            "thumbUrl": "localService/thumb/F46IQC7InJk.jpg",
            "fav": "false",
            "lowResVideoPath": "localService/video/F46IQC7InJk.mp4",
            "fitURL": "", 
            "name": "0011| SKATEHALLE REGENSBURG KEVIN FRITSCHE 10 TRIX.mp4",
            "fileSize": 25311,
            "date": 1487537235,
            "duration" :  0,
            "lensMode": "unknownLensMode"
        },{
            "type": "photo",
            "url": "localService/thumb/3Ht4v1hVmkU.jpg",
            "thumbUrl": "localService/thumb/3Ht4v1hVmkU.jpg",
            "fav": "false",
            "lowResVideoPath": "localService/video/3Ht4v1hVmkU.mp4",
            "fitURL": "", 
            "name": "0012| SKATEHALLE REGENSBURG LEFTOVER.mp4",
            "fileSize": 28302,
            "date": 1492106146,
            "duration" :  0,
            "lensMode": "unknownLensMode"
        },{
            "type": "photo",
            "url": "localService/thumb/2NZRz66tW2A.jpg",
            "thumbUrl": "localService/thumb/2NZRz66tW2A.jpg",
            "fav": "false",
            "lowResVideoPath": "localService/video/2NZRz66tW2A.mp4",
            "fitURL": "", 
            "name": "0013| SKATEHALLE REGENSBURG - SONNTAG ABEND.mp4",
            "fileSize": 8039,
            "date": 1487623867,
            "duration" :  0,
            "lensMode": "unknownLensMode"
        },{
            "type": "photo",
            "url": "localService/thumb/_uFDnmZ8r3M.jpg",
            "thumbUrl": "localService/thumb/_uFDnmZ8r3M.jpg",
            "fav": "false",
            "lowResVideoPath": "localService/video/_uFDnmZ8r3M.mp4",
            "fitURL": "", 
            "name": "0016| SKATEHALLE REGENSBURG - HERWIG KOENIG - 10 TRIX.mp4",
            "fileSize": 28866,
            "date": 1486413473,
            "duration" :  0,
            "lensMode": "unknownLensMode"
        },{
            "type": "photo",
            "url": "localService/thumb/EE1t7vFVknU.jpg",
            "thumbUrl": "localService/thumb/EE1t7vFVknU.jpg",
            "fav": "false",
            "lowResVideoPath": "localService/video/EE1t7vFVknU.mp4",
            "fitURL": "", 
            "name": "0017| SKATEHALLE REGENSBURG - PETER STEGER - 10 TRIX.mp4",
            "fileSize": 22035,
            "date": 1486257905,
            "duration" :  0,
            "lensMode": "unknownLensMode"
        },{
            "type": "photo",
            "url": "localService/thumb/iPuR20W2_z0.jpg",
            "thumbUrl": "localService/thumb/iPuR20W2_z0.jpg",
            "fav": "false",
            "lowResVideoPath": "localService/video/iPuR20W2_z0.mp4",
            "fitURL": "", 
            "name": "0018| SKATEHALLE REGENSBURG - BEN  DILLINGER  - 10 TRIX.mp4",
            "fileSize": 8456,
            "date": 1486257863,
            "duration" :  0,
            "lensMode": "unknownLensMode"
        },{
            "type": "photo",
            "url": "localService/thumb/BZAbFaQ5yAc.jpg",
            "thumbUrl": "localService/thumb/BZAbFaQ5yAc.jpg",
            "fav": "false",
            "lowResVideoPath": "localService/video/BZAbFaQ5yAc.mp4",
            "fitURL": "", 
            "name": "0019| SKATEHALLE REGENSBURG - JULIAN - 10 TRIX.mp4",
            "fileSize": 9523,
            "date": 1492106148,
            "duration" :  0,
            "lensMode": "unknownLensMode"
        },{
            "type": "photo",
            "url": "localService/thumb/PDKQJnzwXN4.jpg",
            "thumbUrl": "localService/thumb/PDKQJnzwXN4.jpg",
            "fav": "false",
            "lowResVideoPath": "localService/video/PDKQJnzwXN4.mp4",
            "fitURL": "", 
            "name": "0020| MARKUS 10 TRIX.mp4",
            "fileSize": 7767,
            "date": 1492106148,
            "duration" :  0,
            "lensMode": "unknownLensMode"
        },{
            "type": "photo",
            "url": "localService/thumb/G4CxtUC0tbc.jpg",
            "thumbUrl": "localService/thumb/G4CxtUC0tbc.jpg",
            "fav": "false",
            "lowResVideoPath": "localService/video/G4CxtUC0tbc.mp4",
            "fitURL": "", 
            "name": "0022| SKATEHALLE REGENSBURG - BASTI - 10 TRIX.mp4",
            "fileSize": 9513,
            "date": 1486257887,
            "duration" :  0,
            "lensMode": "unknownLensMode"
        },{
            "type": "photo",
            "url": "localService/thumb/qav3FSDLZmA.jpg",
            "thumbUrl": "localService/thumb/qav3FSDLZmA.jpg",
            "fav": "false",
            "lowResVideoPath": "localService/video/qav3FSDLZmA.mp4",
            "fitURL": "", 
            "name": "0053| Morass Skoffin - Throne of ignorance.mp4",
            "fileSize": 12586,
            "date": 1471611284,
            "duration" :  0,
            "lensMode": "unknownLensMode"
        },{
            "type": "photo",
            "url": "localService/thumb/KjyUYTOj3ls.jpg",
            "thumbUrl": "localService/thumb/KjyUYTOj3ls.jpg",
            "fav": "false",
            "lowResVideoPath": "localService/video/KjyUYTOj3ls.mp4",
            "fitURL": "", 
            "name": "0281| REGENSBURG STADTLAGERHAUS WOLKENWAND - MASON EXCEEDER.mp4",
            "fileSize": 7422,
            "date": 1503984289,
            "duration" :  0,
            "lensMode": "unknownLensMode"
        },{
            "type": "photo",
            "url": "localService/thumb/SaqvjyDHHNw.jpg",
            "thumbUrl": "localService/thumb/SaqvjyDHHNw.jpg",
            "fav": "false",
            "lowResVideoPath": "localService/video/SaqvjyDHHNw.mp4",
            "fitURL": "", 
            "name": "0282| SK8BATTLE MINIRAMP TEASER.mp4",
            "fileSize": 13033,
            "date": 1437772708,
            "duration" :  0,
            "lensMode": "unknownLensMode"
        },{
            "type": "photo",
            "url": "localService/thumb/hW07AiSFyY8.jpg",
            "thumbUrl": "localService/thumb/hW07AiSFyY8.jpg",
            "fav": "false",
            "lowResVideoPath": "localService/video/hW07AiSFyY8.mp4",
            "fitURL": "", 
            "name": "0294| LONGBOARD TRICKS.mp4",
            "fileSize": 7752,
            "date": 1435036200,
            "duration" :  0,
            "lensMode": "unknownLensMode"
        },{
            "type": "photo",
            "url": "localService/thumb/57J1yB4AGhk.jpg",
            "thumbUrl": "localService/thumb/57J1yB4AGhk.jpg",
            "fav": "false",
            "lowResVideoPath": "localService/video/57J1yB4AGhk.mp4",
            "fitURL": "", 
            "name": "0295| PATTBURG DK SKATEHALLE.mp4",
            "fileSize": 7235,
            "date": 1434840740,
            "duration" :  0,
            "lensMode": "unknownLensMode"
        },{
            "type": "photo",
            "url": "localService/thumb/FrItMdqtdGE.jpg",
            "thumbUrl": "localService/thumb/FrItMdqtdGE.jpg",
            "fav": "false",
            "lowResVideoPath": "localService/video/FrItMdqtdGE.mp4",
            "fitURL": "", 
            "name": "0297| MYSTIC SK8 CUP 2011 BOWL SHREDDING - ANTHRAX - BIG FAT.mp4",
            "fileSize": 9769,
            "date": 1434183300,
            "duration" :  0,
            "lensMode": "unknownLensMode"
        },{
            "type": "photo",
            "url": "localService/thumb/MddcqAVWdC8.jpg",
            "thumbUrl": "localService/thumb/MddcqAVWdC8.jpg",
            "fav": "false",
            "lowResVideoPath": "localService/video/MddcqAVWdC8.mp4",
            "fitURL": "", 
            "name": "0301| Halloween Miniramp Session 2013.mp4",
            "fileSize": 16822,
            "date": 1414473815,
            "duration" :  0,
            "lensMode": "unknownLensMode"
        },{
            "type": "photo",
            "url": "localService/thumb/YZFyUhuQ1QM.jpg",
            "thumbUrl": "localService/thumb/YZFyUhuQ1QM.jpg",
            "fav": "false",
            "lowResVideoPath": "localService/video/YZFyUhuQ1QM.mp4",
            "fitURL": "", 
            "name": "0308| MARKUS vs MÜTZE - S.K.A.T.E. BATTLE REGENSBURG 2012.mp4",
            "fileSize": 15566,
            "date": 1361769146,
            "duration" :  0,
            "lensMode": "unknownLensMode"
        },{
            "type": "photo",
            "url": "localService/thumb/lOx7NPlhyTA.jpg",
            "thumbUrl": "localService/thumb/lOx7NPlhyTA.jpg",
            "fav": "false",
            "lowResVideoPath": "localService/video/lOx7NPlhyTA.mp4",
            "fitURL": "", 
            "name": "0311| MARKUS vs DOMI - S.K.A.T.E. BATTLE REGENSBURG 2012.mp4",
            "fileSize": 15062,
            "date": 1360418491,
            "duration" :  0,
            "lensMode": "unknownLensMode"
        },{
            "type": "photo",
            "url": "localService/thumb/Cnc-wJ_kofM.jpg",
            "thumbUrl": "localService/thumb/Cnc-wJ_kofM.jpg",
            "fav": "false",
            "lowResVideoPath": "localService/video/Cnc-wJ_kofM.mp4",
            "fitURL": "", 
            "name": "0312| Auslosung Runde 2 - S.K.A.T.E. BATTLE REGENSBURG 2012.mp4",
            "fileSize": 16752,
            "date": 1360214591,
            "duration" :  0,
            "lensMode": "unknownLensMode"
        },{
            "type": "photo",
            "url": "localService/thumb/w1w-B2lb1dI.jpg",
            "thumbUrl": "localService/thumb/w1w-B2lb1dI.jpg",
            "fav": "false",
            "lowResVideoPath": "localService/video/w1w-B2lb1dI.mp4",
            "fitURL": "", 
            "name": "0313| MATTHIAS vs QUIRIN - S.K.A.T.E. BATTLE REGENSBURG 2012.mp4",
            "fileSize": 12553,
            "date": 1359191303,
            "duration" :  0,
            "lensMode": "unknownLensMode"
        },{
            "type": "photo",
            "url": "localService/thumb/wt6W5HlD6po.jpg",
            "thumbUrl": "localService/thumb/wt6W5HlD6po.jpg",
            "fav": "false",
            "lowResVideoPath": "localService/video/wt6W5HlD6po.mp4",
            "fitURL": "", 
            "name": "0314| OLF vs ALEX - S.K.A.T.E. BATTLE REGENSBURG 2012.mp4",
            "fileSize": 12683,
            "date": 1357771721,
            "duration" :  0,
            "lensMode": "unknownLensMode"
        },{
            "type": "photo",
            "url": "localService/thumb/y2E435mRXKQ.jpg",
            "thumbUrl": "localService/thumb/y2E435mRXKQ.jpg",
            "fav": "false",
            "lowResVideoPath": "localService/video/y2E435mRXKQ.mp4",
            "fitURL": "", 
            "name": "0315| MÜTZE vs ANDY - S.K.A.T.E. BATTLE REGENSBURG 2012.mp4",
            "fileSize": 12929,
            "date": 1356974836,
            "duration" :  0,
            "lensMode": "unknownLensMode"
        },{
            "type": "photo",
            "url": "localService/thumb/-dW3Tg7Yqwk.jpg",
            "thumbUrl": "localService/thumb/-dW3Tg7Yqwk.jpg",
            "fav": "false",
            "lowResVideoPath": "localService/video/-dW3Tg7Yqwk.mp4",
            "fitURL": "", 
            "name": "0316| MAXI vs MARTIN - S.K.A.T.E. BATTLE REGENSBURG 2012.mp4",
            "fileSize": 11005,
            "date": 1356343940,
            "duration" :  0,
            "lensMode": "unknownLensMode"
        },{
            "type": "photo",
            "url": "localService/thumb/PHksaRTbUfc.jpg",
            "thumbUrl": "localService/thumb/PHksaRTbUfc.jpg",
            "fav": "false",
            "lowResVideoPath": "localService/video/PHksaRTbUfc.mp4",
            "fitURL": "", 
            "name": "0317| ANDRE vs HJ - S.K.A.T.E. BATTLE REGENSBURG 2012.mp4",
            "fileSize": 13533,
            "date": 1356290058,
            "duration" :  0,
            "lensMode": "unknownLensMode"
        },{
            "type": "photo",
            "url": "localService/thumb/dIPTOkbxAPU.jpg",
            "thumbUrl": "localService/thumb/dIPTOkbxAPU.jpg",
            "fav": "false",
            "lowResVideoPath": "localService/video/dIPTOkbxAPU.mp4",
            "fitURL": "", 
            "name": "0318| TOBIAS vs LUKAS - S.K.A.T.E. BATTLE REGENSBURG 2012.mp4",
            "fileSize": 12965,
            "date": 1355116719,
            "duration" :  0,
            "lensMode": "unknownLensMode"
        },{
            "type": "photo",
            "url": "localService/thumb/sN2eRBzQNj8.jpg",
            "thumbUrl": "localService/thumb/sN2eRBzQNj8.jpg",
            "fav": "false",
            "lowResVideoPath": "localService/video/sN2eRBzQNj8.mp4",
            "fitURL": "", 
            "name": "0319| TOM vs KIRBY - S.K.A.T.E. BATTLE REGENSBURG 2012.mp4",
            "fileSize": 11408,
            "date": 1354856383,
            "duration" :  0,
            "lensMode": "unknownLensMode"
        },{
            "type": "photo",
            "url": "localService/thumb/ojW21VKFrGM.jpg",
            "thumbUrl": "localService/thumb/ojW21VKFrGM.jpg",
            "fav": "false",
            "lowResVideoPath": "localService/video/ojW21VKFrGM.mp4",
            "fitURL": "", 
            "name": "0320| S.K.A.T.E. BATTLE REGENSBURG 2012 AULSOUNG.mp4",
            "fileSize": 11157,
            "date": 1354374329,
            "duration" :  0,
            "lensMode": "unknownLensMode"
        },{
            "type": "photo",
            "url": "localService/thumb/QH5q7lr6YP4.jpg",
            "thumbUrl": "localService/thumb/QH5q7lr6YP4.jpg",
            "fav": "false",
            "lowResVideoPath": "localService/video/QH5q7lr6YP4.mp4",
            "fitURL": "", 
            "name": "0321| Fürst 3 ParkCheckOut Pettendorf.mp4",
            "fileSize": 25631,
            "date": 1352568132,
            "duration" :  0,
            "lensMode": "unknownLensMode"
        },{
            "type": "photo",
            "url": "localService/thumb/fbyqA6bH4Ok.jpg",
            "thumbUrl": "localService/thumb/fbyqA6bH4Ok.jpg",
            "fav": "false",
            "lowResVideoPath": "localService/video/fbyqA6bH4Ok.mp4",
            "fitURL": "", 
            "name": "0322| Halloween Jam 2011.mp4",
            "fileSize": 8103,
            "date": 1349912224,
            "duration" :  0,
            "lensMode": "unknownLensMode"
        },{
            "type": "photo",
            "url": "localService/thumb/jtuiVwlIBGE.jpg",
            "thumbUrl": "localService/thumb/jtuiVwlIBGE.jpg",
            "fav": "false",
            "lowResVideoPath": "localService/video/jtuiVwlIBGE.mp4",
            "fitURL": "", 
            "name": "0323| Fürst 3 ParkCheckOut Steinsberg.mp4",
            "fileSize": 16445,
            "date": 1351337051,
            "duration" :  0,
            "lensMode": "unknownLensMode"
        },{
            "type": "photo",
            "url": "localService/thumb/iM3mjr40pnM.jpg",
            "thumbUrl": "localService/thumb/iM3mjr40pnM.jpg",
            "fav": "false",
            "lowResVideoPath": "localService/video/iM3mjr40pnM.mp4",
            "fitURL": "", 
            "name": "0324| SPOTCHECK SKATESESSIONS - TRAILER.mp4",
            "fileSize": 14918,
            "date": 1349214795,
            "duration" :  0,
            "lensMode": "unknownLensMode"
        },{
            "type": "photo",
            "url": "localService/thumb/_di82qZSBqc.jpg",
            "thumbUrl": "localService/thumb/_di82qZSBqc.jpg",
            "fav": "false",
            "lowResVideoPath": "localService/video/_di82qZSBqc.mp4",
            "fitURL": "", 
            "name": "0325| Mystic Skate Cup 2012.mp4",
            "fileSize": 15291,
            "date": 1348732246,
            "duration" :  0,
            "lensMode": "unknownLensMode"
        },{
            "type": "photo",
            "url": "localService/thumb/QtJ9KLChVi0.jpg",
            "thumbUrl": "localService/thumb/QtJ9KLChVi0.jpg",
            "fav": "false",
            "lowResVideoPath": "localService/video/QtJ9KLChVi0.mp4",
            "fitURL": "", 
            "name": "0326| BEATNUTS TEAM MEETS HSFCREW.mp4",
            "fileSize": 11888,
            "date": 1347229371,
            "duration" :  0,
            "lensMode": "unknownLensMode"
        },{
            "type": "photo",
            "url": "localService/thumb/5RP4QagpmNw.jpg",
            "thumbUrl": "localService/thumb/5RP4QagpmNw.jpg",
            "fav": "false",
            "lowResVideoPath": "localService/video/5RP4QagpmNw.mp4",
            "fitURL": "", 
            "name": "0327| SAAL LOCALS ONLY 2011.mp4",
            "fileSize": 17273,
            "date": 1346673966,
            "duration" :  0,
            "lensMode": "unknownLensMode"
        },{
            "type": "photo",
            "url": "localService/thumb/wkezm-hWA7M.jpg",
            "thumbUrl": "localService/thumb/wkezm-hWA7M.jpg",
            "fav": "false",
            "lowResVideoPath": "localService/video/wkezm-hWA7M.mp4",
            "fitURL": "", 
            "name": "0328| PASSAU CONTEST BEST OFF 2010 / 2011.mp4",
            "fileSize": 12267,
            "date": 1346303480,
            "duration" :  0,
            "lensMode": "unknownLensMode"
        },{
            "type": "photo",
            "url": "localService/thumb/uvymg9bEILU.jpg",
            "thumbUrl": "localService/thumb/uvymg9bEILU.jpg",
            "fav": "false",
            "lowResVideoPath": "localService/video/uvymg9bEILU.mp4",
            "fitURL": "", 
            "name": "0329| GAME OF S.K.A.T.E. MINIRAMP.mp4",
            "fileSize": 15469,
            "date": 1345700066,
            "duration" :  0,
            "lensMode": "unknownLensMode"
        },{
            "type": "photo",
            "url": "localService/thumb/6Lj1IUoGBdc.jpg",
            "thumbUrl": "localService/thumb/6Lj1IUoGBdc.jpg",
            "fav": "false",
            "lowResVideoPath": "localService/video/6Lj1IUoGBdc.mp4",
            "fitURL": "", 
            "name": "0331| BEATNUTS BROADCAST TRAILER.mp4",
            "fileSize": 8764,
            "date": 1344438935,
            "duration" :  0,
            "lensMode": "unknownLensMode"
        },{
            "type": "photo",
            "url": "localService/thumb/BWlseW7Won8.jpg",
            "thumbUrl": "localService/thumb/BWlseW7Won8.jpg",
            "fav": "false",
            "lowResVideoPath": "localService/video/BWlseW7Won8.mp4",
            "fitURL": "", 
            "name": "0332| BMXer Special.mp4",
            "fileSize": 7065,
            "date": 1343885055,
            "duration" :  0,
            "lensMode": "unknownLensMode"
        },{
            "type": "photo",
            "url": "localService/thumb/IBue5LwhOHI.jpg",
            "thumbUrl": "localService/thumb/IBue5LwhOHI.jpg",
            "fav": "false",
            "lowResVideoPath": "localService/video/IBue5LwhOHI.mp4",
            "fitURL": "", 
            "name": "0335| D.I.Y. DAYS - REGENSTAUF MINIRAMP.mp4",
            "fileSize": 10626,
            "date": 1339920818,
            "duration" :  0,
            "lensMode": "unknownLensMode"
        },{
            "type": "photo",
            "url": "localService/thumb/C5aSA4-ImHM.jpg",
            "thumbUrl": "localService/thumb/C5aSA4-ImHM.jpg",
            "fav": "false",
            "lowResVideoPath": "localService/video/C5aSA4-ImHM.mp4",
            "fitURL": "", 
            "name": "0340| MYSTIC SKATE CUP 2011 STREET COMPILATION BEST OFF.mp4",
            "fileSize": 12071,
            "date": 1337656767,
            "duration" :  0,
            "lensMode": "unknownLensMode"
        },{
            "type": "photo",
            "url": "localService/thumb/KEX3fq7N23A.jpg",
            "thumbUrl": "localService/thumb/KEX3fq7N23A.jpg",
            "fav": "false",
            "lowResVideoPath": "localService/video/KEX3fq7N23A.mp4",
            "fitURL": "", 
            "name": "0341| LOST & FOUND MYSTIC SK8CUP - MIND BLOWING TRANSFER LIPSLIDE.mp4",
            "fileSize": 9953,
            "date": 1336693092,
            "duration" :  0,
            "lensMode": "unknownLensMode"
        },{
            "type": "photo",
            "url": "localService/thumb/MJ8oM6M2Tp4.jpg",
            "thumbUrl": "localService/thumb/MJ8oM6M2Tp4.jpg",
            "fav": "false",
            "lowResVideoPath": "localService/video/MJ8oM6M2Tp4.mp4",
            "fitURL": "", 
            "name": "0472| SKATEHALLE PFAFFENHOFEN.mp4",
            "fileSize": 10664,
            "date": 1331375936,
            "duration" :  0,
            "lensMode": "unknownLensMode"
        },{
            "type": "photo",
            "url": "localService/thumb/dBuv1C-ZtYY.jpg",
            "thumbUrl": "localService/thumb/dBuv1C-ZtYY.jpg",
            "fav": "false",
            "lowResVideoPath": "localService/video/dBuv1C-ZtYY.mp4",
            "fitURL": "", 
            "name": "0487| KNUT - AIM THE SUN - ORDEAL - VINYL TRYOUT.mp4",
            "fileSize": 11083,
            "date": 1327679564,
            "duration" :  0,
            "lensMode": "unknownLensMode"
        },{
            "type": "photo",
            "url": "localService/thumb/f23QliqphGs.jpg",
            "thumbUrl": "localService/thumb/f23QliqphGs.jpg",
            "fav": "false",
            "lowResVideoPath": "localService/video/f23QliqphGs.mp4",
            "fitURL": "", 
            "name": "0488| KNUT - DISSOLVE - ORDEAL - VINYL TRYOUT.mp4",
            "fileSize": 7736,
            "date": 1327668999,
            "duration" :  0,
            "lensMode": "unknownLensMode"
        },{
            "type": "photo",
            "url": "localService/thumb/CGaMJd10uKY.jpg",
            "thumbUrl": "localService/thumb/CGaMJd10uKY.jpg",
            "fav": "false",
            "lowResVideoPath": "localService/video/CGaMJd10uKY.mp4",
            "fitURL": "", 
            "name": "0509| KNUT - DISSOLVE.mp4",
            "fileSize": 7822,
            "date": 1514680267,
            "duration" :  0,
            "lensMode": "unknownLensMode"
        },{
            "type": "photo",
            "url": "localService/thumb/0RNPvlvQva8.jpg",
            "thumbUrl": "localService/thumb/0RNPvlvQva8.jpg",
            "fav": "false",
            "lowResVideoPath": "localService/video/0RNPvlvQva8.mp4",
            "fitURL": "", 
            "name": "0529| MysticSk8Cup 2011 - barrier sesh - Final - Throwaway.mp4",
            "fileSize": 13071,
            "date": 1317605904,
            "duration" :  0,
            "lensMode": "unknownLensMode"
        },{
            "type": "photo",
            "url": "localService/thumb/yRcXdvJRwEE.jpg",
            "thumbUrl": "localService/thumb/yRcXdvJRwEE.jpg",
            "fav": "false",
            "lowResVideoPath": "localService/video/yRcXdvJRwEE.mp4",
            "fitURL": "", 
            "name": "0530| Flitzer at MysticSk8Cup 2011.mp4",
            "fileSize": 5704,
            "date": 1317605068,
            "duration" :  0,
            "lensMode": "unknownLensMode"
        },{
            "type": "photo",
            "url": "localService/thumb/1EpKQ_jlGgo.jpg",
            "thumbUrl": "localService/thumb/1EpKQ_jlGgo.jpg",
            "fav": "false",
            "lowResVideoPath": "localService/video/1EpKQ_jlGgo.mp4",
            "fitURL": "", 
            "name": "0544| ELEMENT FLAT BBQ - Westpark.mp4",
            "fileSize": 20173,
            "date": 1308412501,
            "duration" :  0,
            "lensMode": "unknownLensMode"
        },{
            "type": "photo",
            "url": "localService/thumb/sIVF3jByvgc.jpg",
            "thumbUrl": "localService/thumb/sIVF3jByvgc.jpg",
            "fav": "false",
            "lowResVideoPath": "localService/video/sIVF3jByvgc.mp4",
            "fitURL": "", 
            "name": "0556| Extrawelt 8000 - Mit dem Rad zur Arbeit.mp4",
            "fileSize": 12878,
            "date": 1296238715,
            "duration" :  0,
            "lensMode": "unknownLensMode"
        },{
            "type": "photo",
            "url": "localService/thumb/1EpKQ_jlGgo.jpg",
            "thumbUrl": "localService/thumb/1EpKQ_jlGgo.jpg",
            "fav": "false",
            "lowResVideoPath": "localService/video/1EpKQ_jlGgo.mp4",
            "fitURL": "", 
            "name": "0544| ELEMENT FLAT BBQ - Westpark.mp4",
            "fileSize": 20173,
            "date": 1308412501,
            "duration" :  0,
            "lensMode": "unknownLensMode"
        },{
            "type": "photo",
            "url": "localService/thumb/sIVF3jByvgc.jpg",
            "thumbUrl": "localService/thumb/sIVF3jByvgc.jpg",
            "fav": "false",
            "lowResVideoPath": "localService/video/sIVF3jByvgc.mp4",
            "fitURL": "", 
            "name": "0556| Extrawelt 8000 - Mit dem Rad zur Arbeit.mp4",
            "fileSize": 12878,
            "date": 1296238715,
            "duration" :  0,
            "lensMode": "unknownLensMode"
        }],"result": 1}