<mvc:View xmlns="sap.m" xmlns:core="sap.ui.core" xmlns:mvc="sap.ui.core.mvc" controllerName="garmin.virb.camerahost.controller.Home">
  <Page title="VIRBControlUI5" >
    <content>
      <core:Fragment fragmentName="garmin.virb.camerahost.view.fragments.DeviceInfo" type="XML" > </core:Fragment>
      <core:Fragment fragmentName="garmin.virb.camerahost.view.fragments.Status" type="XML" > </core:Fragment>
    </content>
    <footer>
      <core:Fragment fragmentName="garmin.virb.camerahost.view.fragments.Footer" type="XML" > </core:Fragment>
    </footer>
  </Page>
</mvc:View>